nsisunbz2/__init__.py
nsisunbz2/cli.py
nsisunbz2/core.py
nsisunbz2-1.0.7.dist-info/LICENSE.txt
nsisunbz2-1.0.7.dist-info/METADATA
nsisunbz2-1.0.7.dist-info/WHEEL
nsisunbz2-1.0.7.dist-info/entry_points.txt
nsisunbz2-1.0.7.dist-info/top_level.txt
nsisunbz2-1.0.7.dist-info/RECORD
