Metadata-Version: 2.2
Name: nsisunbz2
Version: 1.0.7
License-File: LICENSE.txt
